{
  "appPageId" : "c887584e-f884-4234-884f-c032fcf46c96",
  "componentName" : "siteforce:sldsOneColLayout",
  "dataProviders" : [ ],
  "id" : "a60f13d9-fee0-4a91-b5f9-9ad4dc0eebac",
  "label" : "Gerenciamento de conta",
  "regions" : [ {
    "id" : "e04d6d08-f21d-4c38-b9a8-ace579c46710",
    "regionName" : "header",
    "type" : "region"
  }, {
    "components" : [ {
      "componentAttributes" : {
        "richTextValue" : "             <h1 style=\"text-align: center;\">                 <b style=\"font-size: 20px; color: #1e2443;\">Account Management</b>             </h1>             "
      },
      "componentName" : "forceCommunity:richTextInline",
      "id" : "1a2b175e-c2cb-4673-ae81-867646b82700",
      "renderPriority" : "NEUTRAL",
      "renditionMap" : { },
      "type" : "component"
    }, {
      "componentAttributes" : {
        "tabsetConfig" : {
          "UUID" : "a5737748-e9dd-4eca-82ca-02eab28dc04d",
          "activeTab" : "tab1",
          "tabs" : [ {
            "UUID" : "5359f3b1-50ce-4a7b-beab-ff2f6a48d146",
            "allowGuestUser" : false,
            "locked" : false,
            "seedComponents" : [ {
              "attributes" : {
                "customTitle" : "Members",
                "parentRecordId" : "{!CurrentUser.accountId}",
                "relatedListName" : "Users",
                "showBreadCrumbs" : "false",
                "showCustomTitle" : "true",
                "showManualRefreshButton" : "false",
                "showRowNumbers" : "false"
              },
              "fqn" : "forceCommunity:relatedList"
            } ],
            "tabKey" : "tab1",
            "tabName" : "Members"
          }, {
            "UUID" : "616f440d-bb1e-4cf8-aaf3-cbc1f727fe9b",
            "allowGuestUser" : false,
            "locked" : false,
            "seedComponents" : [ {
              "attributes" : {
                "recordId" : "{!CurrentUser.accountId}"
              },
              "fqn" : "forceCommunity:accountBrandRecord"
            } ],
            "tabKey" : "tab2",
            "tabName" : "Branding"
          } ],
          "useOverflowMenu" : false
        }
      },
      "componentName" : "forceCommunity:tabLayout",
      "id" : "a5737748-e9dd-4eca-82ca-02eab28dc04d",
      "regions" : [ {
        "components" : [ {
          "componentAttributes" : {
            "customTitle" : "Members",
            "parentRecordId" : "{!CurrentUser.accountId}",
            "relatedListName" : "Users",
            "showBreadCrumbs" : false,
            "showCustomTitle" : true,
            "showManualRefreshButton" : false,
            "showRowNumbers" : false
          },
          "componentName" : "forceCommunity:relatedList",
          "id" : "d867222b-505a-483b-a2a0-6bc5ccaac49f",
          "renderPriority" : "NEUTRAL",
          "renditionMap" : { },
          "type" : "component"
        } ],
        "id" : "5359f3b1-50ce-4a7b-beab-ff2f6a48d146",
        "regionLabel" : "Members",
        "regionName" : "tab1",
        "renditionMap" : { },
        "type" : "region"
      }, {
        "components" : [ {
          "componentAttributes" : {
            "recordId" : "{!CurrentUser.accountId}"
          },
          "componentName" : "forceCommunity:accountBrandRecord",
          "id" : "4a352d30-fbb9-4fdd-81d6-2641c375386f",
          "renderPriority" : "NEUTRAL",
          "renditionMap" : { },
          "type" : "component"
        } ],
        "id" : "616f440d-bb1e-4cf8-aaf3-cbc1f727fe9b",
        "regionLabel" : "Branding",
        "regionName" : "tab2",
        "renditionMap" : { },
        "type" : "region"
      } ],
      "renderPriority" : "NEUTRAL",
      "renditionMap" : { },
      "type" : "component"
    } ],
    "id" : "f130d833-03d9-4ec0-8308-87d960293339",
    "regionName" : "content",
    "type" : "region"
  }, {
    "id" : "aed4785f-7d95-47b9-8190-ab9b740cbc46",
    "regionName" : "footer",
    "type" : "region"
  }, {
    "components" : [ {
      "componentAttributes" : {
        "customHeadTags" : "",
        "description" : "",
        "title" : "Gerenciamento de conta"
      },
      "componentName" : "forceCommunity:seoAssistant",
      "id" : "21b55fee-c88f-4b89-92aa-4e446fbdc60c",
      "renditionMap" : { },
      "type" : "component"
    } ],
    "id" : "e2fea609-7a45-4866-95c6-f8dc64b7aa8c",
    "regionName" : "sfdcHiddenRegion",
    "type" : "region"
  } ],
  "themeLayoutType" : "Inner",
  "type" : "view",
  "viewType" : "account-management"
}